README.md
__init__.py
gateway_client.py
setup.py
snowflake_utils.py
socket_client.py
ss_gateway_client_sdk.egg-info/PKG-INFO
ss_gateway_client_sdk.egg-info/SOURCES.txt
ss_gateway_client_sdk.egg-info/dependency_links.txt
ss_gateway_client_sdk.egg-info/top_level.txt