Metadata-Version: 2.1
Name: ss-gateway-client-sdk
Version: 1.0.0
Summary: ss gateway from ningbo team,provider many services.include ocr,nlp etc.
Home-page: http://www.sumscope.com
Author: kongshanxuelin
Author-email: 33666490@qq.com
